pytorch_galaxy_datasets/__init__.py
pytorch_galaxy_datasets/download_utils.py
pytorch_galaxy_datasets/galaxy_datamodule.py
pytorch_galaxy_datasets/galaxy_dataset.py
pytorch_galaxy_datasets/prepared_datasets/__init__.py
pytorch_galaxy_datasets/prepared_datasets/candels.py
pytorch_galaxy_datasets/prepared_datasets/dr5.py
pytorch_galaxy_datasets/prepared_datasets/gz2.py
pytorch_galaxy_datasets/prepared_datasets/hubble.py
pytorch_galaxy_datasets/prepared_datasets/internal_urls.py
pytorch_galaxy_datasets/prepared_datasets/legs.py
pytorch_galaxy_datasets/prepared_datasets/rings.py
pytorch_galaxy_datasets/prepared_datasets/tidal.py
pytorch_galaxy_datasets-0.0.2.dist-info/LICENSE
pytorch_galaxy_datasets-0.0.2.dist-info/METADATA
pytorch_galaxy_datasets-0.0.2.dist-info/WHEEL
pytorch_galaxy_datasets-0.0.2.dist-info/top_level.txt
pytorch_galaxy_datasets-0.0.2.dist-info/RECORD
