Metadata-Version: 2.1
Name: pytorch-galaxy-datasets
Version: 0.0.2
Summary: Galaxy Zoo datasets for PyTorch/Lightning
Home-page: https://github.com/mwalmsley/pytorch-galaxy-datasets
Author: Mike Walmsley
Author-email: walmsleymk1@gmail.com
License: UNKNOWN
Platform: UNKNOWN
Classifier: Programming Language :: Python :: 3
Classifier: License :: OSI Approved :: GNU General Public License (GPL)
Classifier: Operating System :: OS Independent
Classifier: Development Status :: 4 - Beta
Classifier: Environment :: GPU :: NVIDIA CUDA
Requires-Python: >=3.7
